cosmic_selection/__init__.py
cosmic_selection/_modidx.py
cosmic_selection/core.py
cosmic_selection/utils.py
cosmic_selection/algorithms/__init__.py
cosmic_selection/algorithms/concepts.py
cosmic_selection/algorithms/scientist_experiment.py
cosmic_selection/objectives/__init__.py
cosmic_selection/objectives/benchmark_funs.py
cosmic_selection/objectives/integer_funs.py
cosmic_selection-0.0.3.dist-info/LICENSE
cosmic_selection-0.0.3.dist-info/METADATA
cosmic_selection-0.0.3.dist-info/WHEEL
cosmic_selection-0.0.3.dist-info/entry_points.txt
cosmic_selection-0.0.3.dist-info/top_level.txt
cosmic_selection-0.0.3.dist-info/RECORD
